.DS_Store
DBApps/BuildStatusUpdater.py
DBApps/DRSUpdate.py
DBApps/DbApp.py
DBApps/SprocColumnError.py
DBApps/__init__.py
DBApps/__main__.py
DBApps/addRelated.py
DBApps/genOutlinesFromQuery.py
DBApps/genWorks.py
DBApps/getNamedWorks.py
DBApps/getReadyRelated.py
DBApps/getReadyWorks.py
DBApps/getworkstest.py
DBApps/readyRelated.py
DBApps/readyWorks.py
DBApps/relatedAdder.py
DBApps/splitWorks.py
DBApps/updateBuildStatus.py
DBApps/DBAppTests/DbAppTest.py
DBApps/DBAppTests/__init__.py
DBApps/DBConfig/__init__.py
DBApps/OrmDb/IATrack.py
DBApps/OrmDb/__init__.py
DBApps/SourceProcessors/WebAdminResults.py
DBApps/SourceProcessors/__init__.py
DBApps/SourceProcessors/test_webAdminResults.py
DBApps/TBRCSrc/__init__.py
DBApps/TBRCSrc/readOutlineXml.py
DBApps/Writers/BuildStatusUpdater.py
DBApps/Writers/CSVWriter.py
DBApps/Writers/DbWriter.py
DBApps/Writers/__init__.py
DBApps/Writers/listwriter.py
DBApps/Writers/progressTimer.py
DBConfig/DBConfig.py
DBConfig/__init__.py
DBConfig/Tests/DBConfigTest.py
DBConfig/Tests/__init__.py
config/__init__.py
config/config.py
config/Tests/DBConfigTest.py
config/Tests/__init__.py
util/__init__.py
util/findWork.py
bdrc_DBApps-1.0.7.dist-info/METADATA
bdrc_DBApps-1.0.7.dist-info/WHEEL
bdrc_DBApps-1.0.7.dist-info/entry_points.txt
bdrc_DBApps-1.0.7.dist-info/top_level.txt
bdrc_DBApps-1.0.7.dist-info/RECORD
