Metadata-Version: 2.1
Name: bdrc-DBApps
Version: 1.0.7
Summary: BDRC DRS DB Apps Suite
Home-page: UNKNOWN
Author: jimk
Author-email: jimk@tbrc.org
License: UNKNOWN
Platform: UNKNOWN
Classifier: Programming Language :: Python :: 3
Classifier: License :: OSI Approved :: MIT License
Classifier: Operating System :: MacOS :: MacOS X
Classifier: Operating System :: OS Independent
Classifier: Development Status :: 5 - Production/Stable
Requires-Python: >=3.7
Requires-Dist: pymysql
Requires-Dist: lxml
Requires-Dist: bdrc-DBAppParser
